multipicking_simulator/__init__.py
multipicking_simulator/constants.py
multipicking_simulator/matching_algorithms.py
multipicking_simulator/analyze/__init__.py
multipicking_simulator/analyze/analyze_utils.py
multipicking_simulator/extract/__init__.py
multipicking_simulator/extract/athena_utils.py
multipicking_simulator/extract/data_extraction_queries.py
multipicking_simulator/extract/data_extraction_utils.py
multipicking_simulator/extract/datadog_utils.py
multipicking_simulator/run/__init__.py
multipicking_simulator/run/run_utils.py
cs_multipicking_simulator-2.0.0.dist-info/METADATA
cs_multipicking_simulator-2.0.0.dist-info/WHEEL
cs_multipicking_simulator-2.0.0.dist-info/top_level.txt
cs_multipicking_simulator-2.0.0.dist-info/RECORD
