Metadata-Version: 2.1
Name: cs-multipicking-simulator
Version: 2.0.0
Summary: CS Dispatcher MP Simulator
Author: CS Dispatcher Operational Research
License: UNKNOWN
Platform: UNKNOWN
Requires-Dist: boto3 (>=1.21.43)
Requires-Dist: dask (>=2022.4.1)
Requires-Dist: gurobipy (>=9.5.1)
Requires-Dist: numpy (>=1.20.2)
Requires-Dist: pandas (>=1.2.4)
Requires-Dist: psycopg2-binary (>=2.9.3)
Requires-Dist: requests (>=2.22.0)
Requires-Dist: pyathena (>=2.5.2)
Requires-Dist: shapely (>=1.8.1)
